pyrutracker-0.5.3.dist-info/DESCRIPTION.rst
pyrutracker-0.5.3.dist-info/pydist.json
pyrutracker-0.5.3.dist-info/RECORD
pyrutracker-0.5.3.dist-info/METADATA
pyrutracker-0.5.3.dist-info/top_level.txt
pyrutracker-0.5.3.dist-info/WHEEL
pyrutracker/__init__.py
pyrutracker/common.py
