Metadata-Version: 2.0
Name: pyrutracker
Version: 0.5.3
Summary: Package to parse rutracker.org forum
Home-page: https://bitbucket.org/wistful/rutracker
Author: wistful
Author-email: wst.public.mail@gmail.com
License: MIT License
Keywords: html,parser,rutracker
Platform: Unix,
Classifier: Development Status :: 5 - Production/Stable
Classifier: Environment :: X11 Applications
Classifier: Intended Audience :: Developers
Classifier: License :: OSI Approved :: MIT License
Classifier: Programming Language :: Python :: 2.7
Classifier: Topic :: Software Development :: Libraries :: Python Modules
Requires-Dist: beautifulsoup4 (>=4)
